mcpstat/__init__.py
mcpstat/core.py
mcpstat/database.py
mcpstat/logging.py
mcpstat/prompts.py
mcpstat/py.typed
mcpstat/tools.py
mcpstat/utils.py
mcpstat-0.1.2.dist-info/METADATA
mcpstat-0.1.2.dist-info/WHEEL
mcpstat-0.1.2.dist-info/licenses/LICENSE
mcpstat-0.1.2.dist-info/RECORD
